<?xml version="1.0" encoding="UTF-8"?>
<?xml-stylesheet type = "text/xsl" href = "http://www.coin-or.org/projects/autoGen.xsl"?>
<projectData xmlns="coin-or.org" xmlns:xsi="http://www.w3.org/2001/XMLSchema-instance" xsi:schemaLocation="coin-or.org http://www.coin-or.org/projects/autoGen.xsd">
  <projectBasics>
    <projectName>Test Tools</projectName>
    <projectRepo>TestTools</projectRepo>
    <projectDescription>
The Test Tools project provides Python scripts to automatically
download, configure, build, test, install, and build binaries
of COIN-OR projects. If a failure is recognized, the scripts can send an e-mail to the corresponding project manager.
    </projectDescription>
    <projectShortDescription>Python scripts to automatically download, configure, build, test, and install COIN-OR projects.</projectShortDescription>
    <projectManager>JP Fasano</projectManager>
    <projectHomePage>https://github.com/coin-or-tools/TestTools</projectHomePage>
    <projectLicense>Common Public License 1.0</projectLicense>
    <projectLicenseURL>http://www.opensource.org/licenses/cpl1.0.php</projectLicenseURL>
    <coinLinkedProjects/>
    <otherLinkedPackages/>
    <projectLanguage>Python</projectLanguage>
    <developmentStatus>
      <activityStatus>Inactive</activityStatus>
      <maturityLevel>2</maturityLevel>
    </developmentStatus>
    <testedPlatforms>
      <platform>
        <operatingSystem>Linux 32 and 64 bit</operatingSystem>
        <compiler>Python 2.5</compiler>
      </platform>
      <platform>
        <operatingSystem>Sun OS Solaris</operatingSystem>
        <compiler>Python 2.4.4</compiler>
      </platform>
      <platform>
        <operatingSystem>AIX Unix</operatingSystem>
        <compiler>Python 2.5</compiler>
      </platform>
      <platform>
        <operatingSystem>Mac OS X</operatingSystem>
        <compiler>Python 2.5</compiler>
      </platform>
      <platform>
        <operatingSystem>Windows XP</operatingSystem>
        <compiler>Python 2.5</compiler>
      </platform>
      <platform>
        <operatingSystem>Windows XP (Cygwin)</operatingSystem>
        <compiler>Python 2.5</compiler>
      </platform>
      <platform>
        <operatingSystem>Windows XP</operatingSystem>
        <compiler>Python 2.5</compiler>
      </platform>
      <platform>
        <operatingSystem>Windows Server 2003 (Cygwin)</operatingSystem>
        <compiler>Python 2.5</compiler>
      </platform>
      <platform>
        <operatingSystem>Windows Server 2003 64 Bit (MinGW)</operatingSystem>
        <compiler>Python 2.5</compiler>
      </platform>
    </testedPlatforms>
    <projectCategories>
      <category>Development tools</category>
    </projectCategories>
  </projectBasics>
  <leftMenuLinks>
    <documentation/>
    <sourceCodeDownload>https://github.com/coin-or-tools/TestTools</sourceCodeDownload>
    <binaryDownload/>
    <mailingList>http://list.coin-or.org/mailman/listinfo/testtools</mailingList>
  </leftMenuLinks>
</projectData>
